Workbook

Sheet Cover
A1: Broken Arrow Training App
A2: IT Project Plan v1.0 - Sprint Tracker
A4: Document Version | B4: 1.0
A5: Created | B5: 2026-04-20
A6: Authored By | B6: Mike (product) with Claude
A7: Planning Horizon | B7: 6 months (26 weeks / 13 x 2-week sprints)
A8: Target Start | B8: 2026-04-27
A9: Target End | B9: 2026-10-25
A10: Scope | B10: 4 gap engines (Terrain completion, MIM novel IP, Descent-Load, Altitude) + Foundation + Integration/Release
A11: Companion Doc | B11: docs/PROJECT_PLAN.md
A12: Strategic Inputs | B12: BA_Executive_Summary_v3.html, BA_Vector1_Science_v3.html, BA_Strategic_Plan_v3.html, BA_DataFlow_v2.html
A14: Sheet | B14: Contents
A15: Overview | B15: High-level phase summary with KPI counts (formula-driven)
A16: Phases | B16: 6 phases with sprints and calendar windows
... A25: Glossary | B25: 24 term abbreviations

Sheet Overview
A1: Overview - counts by status and phase (formula-driven)
A3: Metric | B3: Count | C3: Planned | D3: In Progress | E3: Done | F3: Source
A4: Sprints total | B4: =COUNTA(Sprints!B4:B16) -> 13 | C4: =COUNTIF(Sprints!I4:I16,"Planned") -> 13 | D4: =COUNTIF(Sprints!I4:I16,"In Progress") -> 0 | E4: =COUNTIF(Sprints!I4:I16,"Done") -> 0 | F4: Sprints sheet column I
A5: Phases total | B5: =COUNTA(Phases!A4:A9) -> 6 | C5: - | D5: - | E5: - | F5: Phases sheet
A6: User stories total | B6: =COUNTA(User_Stories!A4:A40) -> 37 | C6: =COUNTIF(User_Stories!G4:G40,"Planned") -> 37 | D6: =COUNTIF(User_Stories!G4:G40,"In Progress") -> 0 | E6: =COUNTIF(User_Stories!G4:G40,"Done") -> 0 | F6: User_Stories sheet column G
A7: Tasks total | B7: =COUNTA(Tasks!B4:B200) -> 66 | C7: =COUNTIF(Tasks!F4:F200,"Planned") -> 66 | D7: =COUNTIF(Tasks!F4:F200,"In Progress") -> 0 | E7: =COUNTIF(Tasks!F4:F200,"Done") -> 0 | F7: Tasks sheet column F
A8: QA items total | B8: =COUNTA(QA_Checklist!A4:A200) -> 67 | C8: - | D8: - | E8: - | F8: QA_Checklist sheet
A9: Test matrix rows | B9: =COUNTA(Test_Matrix!A4:A200) -> 55 | C9: - | D9: - | E9: - | F9: Test_Matrix sheet
A10: Risks total | B10: =COUNTA(Risk_Register!A4:A200) -> 40 | C10: =COUNTIF(Risk_Register!H4:H200,"Open") -> 28 | D10: =COUNTIF(Risk_Register!H4:H200,"Monitor") -> 12 | E10: =COUNTIF(Risk_Register!H4:H200,"Closed") -> 0 | F10: Risk_Register sheet column H
A11: References total | B11: =COUNTA(References!A4:A200) -> 18 | C11: - | D11: - | E11: - | F11: References sheet
A12: Glossary terms total | B12: =COUNTA(Glossary!A4:A200) -> 24 | C12: - | D12: - | E12: - | F12: Glossary sheet
A14: Sprints by phase (formula-driven)
A15: Phase ID | B15: Phase Name | C15: Sprint Count | D15: First Sprint | E15: Last Sprint | F15: Calendar Window
A16: P0 | B16: Foundation | C16: =COUNTIF(Sprints!C4:C16,"P0") -> 1 | D16: 1 | E16: 1 | F16: 2026-04-27 to 2026-05-10
A17: P1 | B17: Terrain Engine | C17: =COUNTIF(Sprints!C4:C16,"P1") -> 3 | D17: 2 | E17: 4 | F17: 2026-05-11 to 2026-06-21
A18: P2 | B18: MIM (Novel IP) | C18: =COUNTIF(Sprints!C4:C16,"P2") -> 3 | D18: 5 | E18: 7 | F18: 2026-06-22 to 2026-08-02
A19: P3 | B19: Descent-Load | C19: =COUNTIF(Sprints!C4:C16,"P3") -> 2 | D19: 8 | E19: 9 | F19: 2026-08-03 to 2026-08-30
A20: P4 | B20: Altitude | C20: =COUNTIF(Sprints!C4:C16,"P4") -> 2 | D20: 10 | E20: 11 | F20: 2026-08-31 to 2026-09-27
A21: P5 | B21: Integration & Release | C21: =COUNTIF(Sprints!C4:C16,"P5") -> 2 | D21: 12 | E21: 13 | F21: 2026-09-28 to 2026-10-25

Sheet Phases
A1: Phases
A3: Phase ID | B3: Name | C3: First Sprint | D3: Last Sprint | E3: Start | F3: End | G3: Description
A4: P0 | B4: Foundation | C4: 1 | D4: 1 | E4: 2026-04-27 | F4: 2026-05-10 | G4: Cross-cutting scaffolding: engine module boundary, feature store, DEM adapter, evidence tiers, coverage gate
A5: P1 | B5: Terrain Engine | C5: 2 | D5: 4 | E5: 2026-05-11 | F5: 2026-06-21 | G5: GAP via Minetti 2002, DEM correction, vertical efficiency, UTMB/ITRA index
A6: P2 | B6: MIM (Novel IP) | C6: 5 | D6: 7 | E6: 2026-06-22 | F6: 2026-08-02 | G6: Bayesian partial-pooled MIM with population priors, per-user personalisation, evidence-tier UI, methodology doc
A7: P3 | B7: Descent-Load | C7: 8 | D7: 9 | E7: 2026-08-03 | F7: 2026-08-30 | G7: Eccentric-TRIMP (Vernillo 2017) and repeated-bout memory (Hyldahl 2017)
A8: P4 | B8: Altitude | C8: 10 | D8: 11 | E8: 2026-08-31 | F8: 2026-09-27 | G8: Hypoxic dose, acclimatization sigmoid (Levine 1997), intensity dampening (West 2013), AMS advisory (Bailey 2021)
A9: P5 | B9: Integration & Release | C9: 12 | D9: 13 | E9: 2026-09-28 | F9: 2026-10-25 | G9: Adaptive Plan Engine ensembles all 5 engines; LLM grounding; release hardening; v1.0.0

Sheet Sprints
A1: Sprints (13 x 2-week, 2026-04-27 to 2026-10-25)
A3: # | B3: Name | C3: Phase | D3: Start | E3: End | F3: Goal | G3: Key Deliverables | H3: Owner | I3: Status
A4: 1 | B4: Foundation | C4: P0 | D4: 2026-04-27 | E4: 2026-05-10 | F4: De-risk downstream sprints with scaffolding | G4: src/engines/ module; featureStore; DEM adapter; evidence tiers; coverage gate; ADR 0001 & 0002 | H4: Claude Code + Mike | I4: Planned
A5: 2 | B5: Terrain-A (GAP / Minetti) | C5: P1 | D5: 2026-05-11 | E5: 2026-05-24 | F5: Grade-Adjusted Pace per Minetti 2002 | G5: minetti.ts; gap.ts; ActivityCard GAP display | H5: Claude Code | I5: Planned
A6: 3 | B6: Terrain-B (DEM correction) | C6: P1 | D6: 2026-05-25 | E6: 2026-06-07 | F6: Replace device elevation with DEM-snapped elevation | G6: dem.ts; usgs3DEP / srtm / asterGDEM adapters; tileCache; CF Worker proxy | H6: Claude Code | I6: Planned
A7: 4 | B7: Terrain-C (VE + UTMB Index) | C7: P1 | D7: 2026-06-08 | E7: 2026-06-21 | F7: Vertical efficiency + UTMB/ITRA indexes | G7: ve.ts; utmbIndex.ts; itraIndex.ts; Terrain dashboard card | H7: Claude Code | I7: Planned
A8: 5 | B8: MIM-A (Priors + Bayes scaffold) | C8: P2 | D8: 2026-06-22 | E8: 2026-07-05 | F8: Population priors + Bayesian posterior in shadow mode | G8: priors.json; bayes.ts; fit-mim-priors.ts; shadow-mode flag | H8: Claude Code + Mike | I8: Planned
A9: 6 | B9: MIM-B (Personalisation loop) | C9: P2 | D9: 2026-07-06 | E9: 2026-07-19 | F9: Soreness prompt + nightly posterior update, cohort flip | G9: SorenessPrompt; update-posteriors.py; learner.ts; cohort service | H9: Claude Code + Mike | I9: Planned
A10: 7 | B10: MIM-C (Evidence-tier UI + methodology) | C10: P2 | D10: 2026-07-20 | E10: 2026-08-02 | F10: Explainability UI + methodology doc + 100% rollout | G10: MIMEvidenceBadge.tsx; mim-methodology.md; canary runbook | H10: Claude Code + Mike | I10: Planned
A11: 8 | B11: Descent-A (Eccentric-TRIMP) | C11: P3 | D11: 2026-08-03 | E11: 2026-08-16 | F11: Eccentric dose per descent bucket | G11: eccentric.ts; TRIMPRecord extension; Eccentric load strip | H11: Claude Code | I11: Planned
A12: 9 | B12: Descent-B (Repeated-bout memory) | C12: P3 | D12: 2026-08-17 | E12: 2026-08-30 | F12: Protection factor for back-to-back bouts | G12: boutMemory.ts; readiness integration; ADR 0003 | H12: Claude Code | I12: Planned
A13: 10 | B13: Altitude-A (Dose + Sigmoid) | C13: P4 | D13: 2026-08-31 | E13: 2026-09-13 | F13: Hypoxic dose accumulator + acclimatization sigmoid | G13: dose.ts; acclimatization.ts; AltitudeTripForm | H13: Claude Code + Mike | I13: Planned
A14: 11 | B14: Altitude-B (Dampening + AMS) | C14: P4 | D14: 2026-09-14 | E14: 2026-09-27 | F14: VO2max-loss dampening + AMS advisory | G14: dampening.ts; ams.ts; CoachSnapshot altitude | H14: Claude Code + Mike | I14: Planned
A15: 12 | B15: Ensemble (Adaptive Plan Engine) | C15: P5 | D15: 2026-09-28 | E15: 2026-10-11 | F15: Compose 5 engines into DailyPrescription + LLM grounding | G15: adaptive/index.ts; ADR 0004; coachGolden tests; Why-this-workout card | H15: Claude Code + Mike | I15: Planned
A16: 13 | B16: Release hardening | C16: P5 | D16: 2026-10-12 | E16: 2026-10-25 | F16: Performance, offline-first, a11y, release v1.0.0 | G16: tinybench perf suite; axe-core CI; release runbook; CHANGELOG.md; v1.0.0 tag | H16: Claude Code + Mike | I16: Planned

Sheet Preservation
A1: Preservation Matrix — shipped code ↔ plan decisions
A2: No shipped feature is silently dropped. Every row below names a surface in the shipped app and the decision the plan takes. Mirrors PROJECT_PLAN.md §4.4.
A3: Legend: ✅ Preserve = unchanged · 🔄 Extend = kept + additive props · 📦 Re-parent = kept, moved · ✂ Streamline = content consolidated · 🆕 Add = net-new · ❌ Deprecate = replaced (justified)
A5: Group | B5: Shipped surface | C5: Decision | D5: Sprint that touches | E5: File path | F5: Notes
A6: Summary tab | B6: TodayBriefing | C6: 🔄 Extend | D6: S12 | E6: src/components/TodayBriefing.tsx | F6: Riley hero card wraps it; 'Why' collapsible gains MIM + Altitude bullets
A7: Summary tab | B7: VitalsGrid | C7: ✅ Preserve | D7: — | E7: src/components/VitalsGrid.tsx | F7: HRV / RHR / Sleep / Body Battery with sparklines. No change.
A8: Summary tab | B8: InjuryRiskAlerts | C8: 🔄 Extend | D8: S8, S11 | E8: src/components/InjuryRiskAlerts.tsx | F8: Adds descent-load red-flag channel + AMS red-flag channel
A9: Summary tab | B9: PerformanceSnapshot | C9: ✅ Preserve | D9: — | E9: src/components/PerformanceSnapshot.tsx | F9: CTL / ATL / TSB / ACWR scale bars. Reads existing CoachSnapshot.
A10: Summary tab | B10: TRIMPBreakdown | C10: 🔄 Extend | D10: S8 | E10: src/components/TRIMPBreakdown.tsx | F10: New eccentricDose series stacked onto existing sport-type bars
A11: Summary tab | B11: WhatChangedCard | C11: 🔄 Extend | D11: S12 | E11: src/components/WhatChangedCard.tsx | F11: Narrative source switches to Adaptive Plan Engine output
A12: Summary tab | B12: WeekAtAGlance | C12: ✅ Preserve | D12: — | E12: src/components/WeekAtAGlance.tsx | F12: 7 readiness dots. Unchanged.
A13: Summary tab | B13: Riley hero card | C13: 🆕 Add | D13: S1 (stub), S12 (real) | E13: src/components/RileyHeroCard.tsx (new) | F13: Wraps TodayBriefing; persona + synthesis + 'What's driving this' collapsible
A14: Plan tab | B14: PlanView | C14: ✂ Streamline | D14: S12 | E14: src/components/PlanView.tsx | F14: 'This week, per Riley' narration card prepended above existing list
A15: Plan tab | B15: WeekStrip | C15: ✅ Preserve | D15: — | E15: src/components/WeekStrip.tsx | F15: M-T-W-T-F-S-S pill strip. Unchanged.
A16: Plan tab | B16: WorkoutCard | C16: 🔄 Extend | D16: S2–S4, S5–S7, S11 | E16: src/components/WorkoutCard.tsx | F16: Terrain / MIM / Altitude tier-chip slots added; existing layout preserved
... A51: Infra | B51: deploy.yml (GitHub Actions) | C51: 🔄 Extend | D51: S1 | E51: .github/workflows/deploy.yml | F51: Coverage gate raised to 80/80/80/80; no other job changes
A53: Summary
A54: Preserve | B54: =COUNTIF(C6:C51,"*Preserve*") -> 24
A55: Extend | B55: =COUNTIF(C6:C51,"*Extend*") -> 13
A56: Re-parent | B56: =COUNTIF(C6:C51,"*Re-parent*") -> 3
A57: Streamline | B57: =COUNTIF(C6:C51,"*Streamline*") -> 1
A58: Add | B58: =COUNTIF(C6:C51,"*Add*") -> 5
A59: Deprecate | B59: =COUNTIF(C6:C51,"*Deprecate*") -> 0
A60: TOTAL | B60: =COUNTA(B6:B51) -> 46
A62: Key commitments
A63: · 0 deprecations — no shipped component is being replaced.
A64: · All 12 shipped test files must stay green at every sprint's Definition-of-Done.
A65: · Static MIM_MATRIX retained as cold-start fallback alongside new Bayesian posterior.
A66: · CoachSnapshot type additions are append-only — no existing fields renamed or removed.
A67: · All 5 Settings rows (Profile / CoachPersona / AboutMe / HRZone / Integrations / CacheDiagnostics / Privacy) ship as-is; plan only ADDS Trips + Methodology.

Sheet User_Stories
A1: User Stories (INVEST form)
A3: ID | B3: Sprint | C3: Persona | D3: Story (As a X, I want Y so that Z) | E3: Priority | F3: Points | G3: Status
A4: US-S1-01 | B4: 1 | C4: Developer | D4: Single src/engines/ module boundary so engine code stays separable from UI | E4: Must | F4: 3 | G4: Planned
A5: US-S1-02 | B5: 1 | C5: Developer | D5: Typed FeatureStore interface so every engine consumes a consistent shape | E5: Must | F5: 5 | G5: Planned
A6: US-S1-03 | B6: 1 | C6: Developer | D6: DEM adapter interface so DEM sources can be swapped without touching engines | E6: Must | F6: 3 | G6: Planned
A7: US-S1-04 | B7: 1 | C7: Developer | D7: Evidence-tier system so every engine coefficient can be tagged T1-T4 | E7: Must | F7: 2 | G7: Planned
A8: US-S1-05 | B8: 1 | C8: Developer | D8: Coverage gating enforced in CI | E8: Must | F8: 2 | G8: Planned
A9: US-S2-01 | B9: 2 | C9: Athlete | D9: Trail pace normalised to flat-equivalent GAP | E9: Must | F9: 5 | G9: Planned
A10: US-S2-02 | B10: 2 | C10: Athlete | D10: GAP shown next to raw pace in activity view | E10: Must | F10: 2 | G10: Planned
A11: US-S3-01 | B11: 3 | C11: Athlete | D11: Elevation gain matches reality (+/-3%), not barometer drift | E11: Must | F11: 8 | G11: Planned
A12: US-S3-02 | B12: 3 | C12: Developer | D12: DEM tile caching so hot routes don't re-fetch | E12: Should | F12: 3 | G12: Planned
A13: US-S4-01 | B13: 4 | C13: Athlete | D13: Vertical Efficiency tracked so power-hiking improvement is visible | E13: Must | F13: 5 | G13: Planned
A14: US-S4-02 | B14: 4 | C14: Athlete | D14: UTMB Index estimate based on recent races | E14: Should | F14: 5 | G14: Planned
A15: US-S5-01 | B15: 5 | C15: Data-aware dev | D15: Population priors fit from fleet data | E15: Must | F15: 8 | G15: Planned
... A40: US-S13-04 | B40: 13 | C40: Developer | D40: Full release checklist + v1.0.0 tag | E40: Must | F40: 3 | G40: Planned

Sheet Acceptance_Criteria
A1: Acceptance Criteria (Gherkin: Given / When / Then)
A3: Story ID | B3: AC # | C3: Given | D3: When | E3: Then
A4: US-S1-01 | B4: 1 | C4: repo state at sprint start | D4: I open src/engines/index.ts | E4: it re-exports readiness, mim, terrain, descent, altitude namespaces
A5: US-S1-01 | B5: 2 | C5: src/engines/readiness/ exists | D5: I compare to existing src/utils/readiness.ts | E5: existing symbols re-exported with no behaviour change (trimp.test.ts, readiness.test.ts still green)
A6: US-S1-02 | B6: 1 | C6: a fresh FeatureStore | D6: I write+read daily/activity/athlete/elevationTile/hypoxicExposure/eccentricBucket records | E6: round-trip is lossless
A7: US-S1-03 | B7: 1 | C7: Open-Elevation adapter mock | D7: DEMAdapter.lookup(lat, lon) is called | E7: it returns an ElevationSample within expected shape
A8: US-S1-04 | B8: 1 | C8: an EvidenceTier union in code | D8: I wrap a MIM matrix entry in TieredValue<number> | E8: tier and citation are visible at the call site
A9: US-S1-05 | B9: 1 | C9: vitest.config.ts with coverage thresholds at 80 | D9: I drop below 80% in a PR | E9: CI fails the coverage step
A10: US-S2-01 | B10: 1 | C10: an activity with altitude + time streams | D10: computeGAP(activity) runs | E10: GAP >= pace for net-uphill, <= pace for net-downhill (+/-2% vs hand-computed fixture)
A11: US-S2-01 | B11: 2 | C11: a flat activity (|grade|<1%) | D11: computeGAP runs | E11: GAP ~= pace within 0.5%
A12: US-S2-01 | B12: 3 | C12: Minetti 2002 polynomial in code | D12: a reviewer reads minetti.ts header | E12: the PMID 12235031 citation is present
A13: US-S2-02 | B13: 1 | C13: an activity with GAP computable | D13: the Activity card renders | E13: GAP is shown next to raw pace
A14: US-S2-02 | B14: 2 | C14: an activity without altitude stream | D14: the Activity card renders | E14: GAP field shows '-' (not 0 or NaN)
A15: US-S3-01 | B15: 1 | C15: an activity with lat/lon stream and DEM coverage | D15: correctElevation(activity) runs | E15: gain is within 3% of a known-good reference
... A50: US-S13-04 | B50: 1 | C50: end of Sprint 13 | D50: release checklist completed | E50: v1.0.0 tag pushed; CHANGELOG synthesised; deploy workflow green

Sheet Tasks
A1: Engineering Tasks (for Claude Code, with file paths)
A3: Sprint | B3: Task ID | C3: Area | D3: Description | E3: File Path(s) | F3: Status
A4: 1 | B4: T1.1 | C4: Arch | D4: Create src/engines/ subfolders + index.ts re-exports | E4: src/engines/{readiness,mim,terrain,descent,altitude}/ | F4: Planned
A5: 1 | B5: T1.2 | C5: Types | D5: FeatureStore interface + InMemoryFeatureStore | E5: src/engines/featureStore.ts | F5: Planned
A6: 1 | B6: T1.3 | C6: Adapter | D6: DEMAdapter interface + Open-Elevation adapter + stubs | E6: src/engines/adapters/*.ts | F6: Planned
A7: 1 | B7: T1.4 | C7: Types | D7: EvidenceTier + TieredValue<T> | E7: src/engines/evidence.ts | F7: Planned
A8: 1 | B8: T1.5 | C8: CI | D8: Coverage thresholds 80/80/80/80 + enforce on CI | E8: vitest.config.ts + .github/workflows/deploy.yml | F8: Planned
A9: 1 | B9: T1.6 | C9: Docs | D9: ADR 0001 engine layout + ADR 0002 evidence tiers | E9: docs/adr/0001-engine-module-layout.md, docs/adr/0002-evidence-tiers.md | F9: Planned
A10: 1 | B10: T1.7 | C10: Obs | D10: Structured logging via debug with ba:engine:* prefix | E10: src/engines/* | F10: Planned
A11: 1 | B11: T1.8 | C11: Docs | D11: README Quickstart + PR template | E11: README.md, .github/PULL_REQUEST_TEMPLATE.md | F11: Planned
A12: 2 | B12: T2.1 | C12: Engine | D12: Minetti cost-of-locomotion polynomial (grade -45..+45%) | E12: src/engines/terrain/minetti.ts | F12: Planned
A13: 2 | B13: T2.2 | C13: Engine | D13: computeGAP(activity) with guardrails | E13: src/engines/terrain/gap.ts | F13: Planned
A14: 2 | B14: T2.3 | C14: UI | D14: Render GAP next to pace on ActivityCard | E14: src/components/ActivityCard.tsx | F14: Planned
A15: 2 | B15: T2.4 | C15: Snapshot | D15: Populate CoachSnapshot.engines.terrain.gap | E15: src/utils/coachSnapshot.ts | F15: Planned
... A69: 13 | B69: T13.5 | C69: Release | D69: Version bump to 1.0.0 and tag v1.0.0 | E69: package.json + git tag | F69: Planned

Sheet QA_Checklist
A1: QA/QC Checklist (per sprint)
A3: Sprint | B3: Area | C3: Item | D3: Status
A4: 1 | B4: CI | C4: npm ci && npm run lint && npm test green locally and on CI | D4: Open
A5: 1 | B5: Coverage | C5: >=80% on new src/engines/ | D5: Open
A6: 1 | B6: Regression | C6: All existing 12 test files unchanged | D6: Open
A7: 1 | B7: Docs | C7: ADR 0001 and 0002 reviewed | D7: Open
A8: 1 | B8: UX | C8: No user-facing change (smoke: readiness still renders) | D8: Open
A9: 1 | B9: Release | C9: git tag v0.1.0 on merge | D9: Open
A10: 2 | B10: Science | C10: Minetti polynomial uses published coefficients with PMID 12235031 comment | D10: Open
A11: 2 | B11: Fixture | C11: Real-world fixture (Broken Arrow 26K) included | D11: Open
A12: 2 | B12: UX | C12: GAP label + tooltip citing Minetti 2002 | D12: Open
A13: 2 | B13: Safety | C13: No negative GAP, NaN, or Infinity; runtime assertions | D13: Open
A14: 2 | B14: Perf | C14: GAP on 7,200-sample activity < 50 ms | D14: Open
A15: 3 | B15: Adapter | C15: Mock HTTP for every adapter path | D15: Open
... A70: 13 | B70: Release | C70: package.json 1.0.0; git tag v1.0.0; deploy workflow green | D70: Open

Sheet Test_Matrix
A1: Test Matrix (Unit / Integration / Regression / Golden / E2E / Perf / a11y)
A3: Sprint | B3: Layer | C3: File / Suite | D3: What it asserts
A4: 1 | B4: Unit | C4: featureStore.test.ts | D4: round-trip, overwrite, time-range query
A5: 1 | B5: Unit | C5: evidence.test.ts | D5: tier ordering, citation string invariant
A6: 1 | B6: Unit | C6: demAdapter.openElevation.test.ts | D6: HTTP mock 200/404/timeout
A7: 1 | B7: Regression | C7: existing 12 test files | D7: all still green after refactor
A8: 2 | B8: Unit | C8: minetti.test.ts | D8: 10 grade points vs published table
A9: 2 | B9: Unit | C9: gap.test.ts | D9: 6 fixtures inc flat, up5, up10, down5, rolling, bad-data
A10: 2 | B10: Unit | C10: gap.perf.test.ts | D10: 7,200-sample activity < 50 ms
A11: 2 | B11: Integration | C11: terrain.integration.test.ts | D11: GAP populated into CoachSnapshot
A12: 2 | B12: E2E | C12: Playwright smoke | D12: Activity card renders GAP label
A13: 3 | B13: Unit | C13: tileCache.test.ts | D13: LRU eviction + TTL expiry
A14: 3 | B14: Unit | C14: dem.region.test.ts | D14: region dispatch table
A15: 3 | B15: Unit | C15: usgs3DEP.test.ts | D15: mock HTTP
... A58: 13 | B58: Regression | C58: full suite | D58: 0 failures

Sheet Risk_Register
A1: Risk Register (plan-level + sprint-level)
A3: Risk ID | B3: Scope | C3: Risk | D3: Prob | E3: Impact | F3: Owner | G3: Mitigation | H3: Status
A4: R-P-01 | B4: Plan | C4: Insufficient fleet data for MIM priors | D4: H | E4: H | F4: Mike | G4: Tag low-N priors T4; ship with legacy fallback | H4: Monitor
A5: R-P-02 | B5: Plan | C5: DEM bandwidth costs | D5: M | E5: M | F5: Mike | G5: Tile cache + Cloudflare Worker proxy | H5: Monitor
A6: R-P-03 | B6: Plan | C6: Coach LLM hallucinates engine values | D6: M | E6: H | F6: Mike | G6: Golden tests + explicit prompt + post-hoc validator | H6: Monitor
A7: R-P-04 | B7: Plan | C7: Soreness-prompt fatigue hurts compliance | D7: M | E7: M | F7: Mike | G7: Cap 3/week + smart skip | H7: Monitor
A8: R-P-05 | B8: Plan | C8: Medical-liability language in AMS advisory | D8: M | E8: H | F8: Mike | G8: Legal copy review; informational framing | H8: Monitor
A9: R-P-06 | B9: Plan | C9: Scope creep into Readiness / Terra / billing | D9: H | E9: M | F9: Mike | G9: Explicit out-of-scope list; backlog anything new | H9: Monitor
A10: R-P-07 | B10: Plan | C10: CI flakiness masks real regressions | D10: M | E10: M | F10: Claude | G10: docs/flaky-tests.md + 1-sprint fix SLA | H10: Monitor
A11: R-P-08 | B11: Plan | C11: Privacy leak via cross-athlete analytics | D11: L | E11: H | F11: Mike | G11: Hashed IDs + per-sprint privacy review | H11: Monitor
A12: R-P-09 | B12: Plan | C12: Perf regression from engine stack | D12: M | E12: H | F12: Claude | G12: Perf budgets enforced from S12 | H12: Monitor
A13: R-P-10 | B13: Plan | C13: a11y backlog at release | D13: M | E13: M | F13: Mike | G13: axe-core in CI from S1; sweep in S13 | H13: Monitor
A14: R-P-11 | B14: Plan | C14: iOS HealthKit altitude path unreliable | D14: H | E14: M | F14: Mike | G14: Manual altitude-trip form as first-class UX | H14: Monitor
... A43: R-S13-2 | B43: S13 | C43: a11y backlog exceeds sprint capacity | D43: M | E43: M | F43: Mike | G43: Defer non-critical to v1.1 backlog | H43: Open

Sheet References
A1: Peer-reviewed references cited in the plan
A3: Author(s) | B3: Year | C3: Title | D3: Venue | E3: Tier | F3: PMID | G3: Source
A4: Banister EW | B4: 1991 | C4: Modeling elite athletic performance (TRIMP) | D4: In: MacDougall JD, ed. Physiological Testing of the High Performance Athlete | E4: T1 | F4: - | G4: Book chapter
A5: Bailey DM et al | B5: 2021 | C5: Altitude training and the AMS consensus | D5: High Alt Med Biol | E5: T1 | F5: 34001987 | G5: PubMed
A6: Chapman RF et al | B6: 2014 | C6: Defining the 'dose' of altitude training | D6: J Appl Physiol 116(6):595-603 | E6: T2 | F6: 24264287 | G6: PubMed
A7: Delp SL et al | B7: 2007 | C7: OpenSim framework | D7: IEEE Trans Biomed Eng 54(11):1940-1950 | E7: T3 | F7: 18018689 | G7: PubMed
A8: Efron B, Morris C | B8: 1977 | C8: Stein's paradox in statistics | D8: Sci Am 236(5):119-127 | E8: T3 | F8: - | G8: Journal
A9: Gabbett TJ | B9: 2016 | C9: Training-injury prevention paradox (ACWR) | D9: Br J Sports Med 50(5):273-280 | E9: T1 | F9: 26758673 | G9: PubMed
A10: Gelman A et al | B10: 2013 | C10: Bayesian Data Analysis 3rd ed | D10: CRC Press | E10: T3 | F10: - | G10: Book
A11: Giovanelli N et al | B11: 2016 | C11: Energetics of vertical kilometer foot races | D11: Eur J Appl Physiol | E11: T2 | F11: 27116915 | G11: PubMed
A12: Guyatt GH et al | B12: 2008 | C12: GRADE evidence framework | D12: BMJ 336(7650):924-926 | E12: T1 | F12: 18436948 | G12: PubMed
A13: Hyldahl RD et al | B13: 2017 | C13: Mechanisms of repeated bout effect | D13: Exerc Sport Sci Rev | E13: T1 | F13: 28457071 | G13: PubMed
A14: Levine BD, Stray-Gundersen J | B14: 1997 | C14: Live high train low | D14: J Appl Physiol 83(1):102-112 | E14: T1 | F14: 9216968 | G14: PubMed
A15: Meeusen R et al | B15: 2013 | C15: Overtraining syndrome ECSS/ACSM consensus | D15: Med Sci Sports Exerc | E15: T1 | F15: 23247672 | G15: PubMed
... A21: West JB | B21: 2013 | C21: High Altitude Medicine and Physiology 5th ed | D21: CRC Press | E21: T3 | F21: - | G21: Book

Sheet Glossary
A1: Glossary
A3: Term | B3: Definition
A4: ACWR | B4: Acute:Chronic Workload Ratio (Gabbett 2016)
A5: AMS | B5: Acute Mountain Sickness (Bailey 2021)
A6: ATE | B6: Readiness composite score (src/utils/readiness.ts)
A7: ATL | B7: Acute Training Load (~7-day EMA)
A8: Banister TRIMP | B8: HR-based training impulse (Banister 1991)
A9: Bayesian partial pooling | B9: Shrinkage toward population mean (Efron-Morris 1977 / Gelman BDA3)
A10: CTL | B10: Chronic Training Load (~42-day EMA)
A11: DEM | B11: Digital Elevation Model (USGS 3DEP / SRTM / ASTER GDEM / Open-Elevation)
A12: Descent-Load | B12: Eccentric muscle damage dose from downhill (Vernillo 2017)
A13: DoD | B13: Definition of Done
A14: DOMS | B14: Delayed-Onset Muscle Soreness (carry-forward in trimp.ts)
... A27: VE | B27: Vertical Efficiency (Giovanelli 2016 crossover)
